llm_detector/__init__.py
llm_detector/aggregation.py
llm_detector/api.py
llm_detector/cli.py
llm_detector/runtime.py
llm_detector/textops.py
llm_detector/types.py
llm_detector/assets/__init__.py
llm_detector/assets/default_baselines.json.gz
llm_detector/assets/default_model.joblib
llm_detector/assets/tokenizers/bert_base_uncased_tokenizer.json
llm_detector/assets/tokenizers/gpt2_tokenizer.json
llm_detector/assets/tokenizers/openai_gpt_oss_20b_tokenizer.json
llm_detector/assets/tokenizers/roberta_base_tokenizer.json
llm_detector/baselines/__init__.py
llm_detector/baselines/cli.py
llm_detector/features/__init__.py
llm_detector/features/divergence.py
llm_detector/features/registry.py
llm_detector/features/statistical.py
llm_detector/features/tokenizer.py
llm_detector/features/vectorizer.py
llm_detector/models/__init__.py
llm_detector/models/logistic.py
llm_detector/training/__init__.py
llm_detector/training/cli.py
llm_detector/training/dataset.py
llm_detector/training/pipeline.py
llm_detector/training/sources/__init__.py
llm_detector/training/sources/base.py
llm_detector/training/sources/formal.py
llm_detector/training/sources/human.py
llm_detector/training/sources/llm.py
llm_detector/training/sources/llm_2024.py
llm_detector/training/sources/registry.py
llm_detector/training/sources/social_media.py
llm_detector/training/sources/utils.py
llm_detector-0.2.0.dist-info/METADATA
llm_detector-0.2.0.dist-info/WHEEL
llm_detector-0.2.0.dist-info/entry_points.txt
llm_detector-0.2.0.dist-info/top_level.txt
llm_detector-0.2.0.dist-info/RECORD
