Metadata-Version: 2.4
Name: llm-detector
Version: 0.2.0
Summary: Transparent, probabilistic classification of text as human-generated or LLM-generated
Author-email: Michael Bommarito <michael.bommarito@gmail.com>
License: MIT
Project-URL: Homepage, https://github.com/mjbommar/llm-detector
Project-URL: Bug Tracker, https://github.com/mjbommar/llm-detector/issues
Project-URL: Repository, https://github.com/mjbommar/llm-detector
Keywords: llm-detection,ai-detection,text-classification,machine-learning,nlp,natural-language-processing,gpt-detection,chatgpt-detection,ai-generated-text,human-vs-ai,text-analysis,statistical-nlp
Classifier: Development Status :: 3 - Alpha
Classifier: Intended Audience :: Developers
Classifier: Intended Audience :: Science/Research
Classifier: License :: OSI Approved :: MIT License
Classifier: Programming Language :: Python :: 3
Classifier: Programming Language :: Python :: 3.11
Classifier: Programming Language :: Python :: 3.12
Classifier: Topic :: Scientific/Engineering :: Artificial Intelligence
Classifier: Topic :: Text Processing :: Linguistic
Classifier: Topic :: Software Development :: Libraries :: Python Modules
Classifier: Operating System :: OS Independent
Requires-Python: >=3.11
Requires-Dist: nupunkt-rs>=0.1.1
Requires-Dist: tokenizers>=0.20.0
Provides-Extra: training
Requires-Dist: scikit-learn>=1.6.0; extra == "training"
Requires-Dist: datasets>=2.19; extra == "training"
Requires-Dist: zstandard>=0.22; extra == "training"
Requires-Dist: pyarrow>=12; extra == "training"
Requires-Dist: tqdm>=4.66; extra == "training"
Provides-Extra: dev
Requires-Dist: scikit-learn>=1.6.0; extra == "dev"
Requires-Dist: pytest>=8.4.2; extra == "dev"
Requires-Dist: pytest-cov>=4.1; extra == "dev"
Requires-Dist: pytest-benchmark>=5.1.0; extra == "dev"
Requires-Dist: ruff>=0.5.0; extra == "dev"
